piapia/__init__.py
piapia/hello.py
piapia-0.0.2.dist-info/METADATA
piapia-0.0.2.dist-info/WHEEL
piapia-0.0.2.dist-info/top_level.txt
piapia-0.0.2.dist-info/RECORD
