Metadata-Version: 2.1
Name: piapia
Version: 0.0.2
Summary: Pia pia
Home-page: UNKNOWN
Author: Yuchi Hsu
Author-email: yuchihsu0512@gmail.com
License: UNKNOWN
Keywords: first package
Platform: UNKNOWN
Classifier: Development Status :: 1 - Planning
Classifier: Intended Audience :: Developers
Classifier: Programming Language :: Python :: 3
Classifier: Operating System :: Unix
Classifier: Operating System :: MacOS :: MacOS X
Classifier: Operating System :: Microsoft :: Windows
